pyppl_flowchart.py
pyppl_flowchart-0.1.5.dist-info/entry_points.txt
pyppl_flowchart-0.1.5.dist-info/LICENSE
pyppl_flowchart-0.1.5.dist-info/WHEEL
pyppl_flowchart-0.1.5.dist-info/METADATA
pyppl_flowchart-0.1.5.dist-info/RECORD
