Metadata-Version: 2.1
Name: pyppl-flowchart
Version: 0.1.5
Summary: Generating flowchart for PyPPL
Home-page: https://github.com/pwwang/pyppl_flowchart
License: MIT
Author: pwwang
Author-email: pwwang@pwwang.com
Requires-Python: >=3.6,<4.0
Classifier: License :: OSI Approved :: MIT License
Classifier: Programming Language :: Python :: 3
Classifier: Programming Language :: Python :: 3.6
Classifier: Programming Language :: Python :: 3.7
Classifier: Programming Language :: Python :: 3.8
Requires-Dist: graphviz (>=0.11,<0.12)
Requires-Dist: pyppl
Project-URL: Repository, https://github.com/pwwang/pyppl_flowchart
